cbi_ddd/__init__.py
cbi_ddd/helpers/__init__.py
cbi_ddd/helpers/dt.py
cbi_ddd/helpers/rabbitmq.py
cbi_ddd/interfaces/__init__.py
cbi_ddd/interfaces/base_app_settings.py
cbi_ddd/interfaces/data_filter.py
cbi_ddd/interfaces/data_model.py
cbi_ddd/interfaces/data_model_dto_opts.py
cbi_ddd/interfaces/data_model_opts.py
cbi_ddd/interfaces/data_model_repository.py
cbi_ddd/interfaces/dto_model.py
cbi_ddd/interfaces/dto_repository.py
cbi_ddd/interfaces/errors.py
cbi_ddd/interfaces/settings/__init__.py
cbi_ddd/interfaces/settings/rabbitmq.py
cbi_ddd/repositories/__init__.py
cbi_ddd/repositories/settings_repository.py
cbi_ddd/repositories/storage_repository.py
cbi_ddd/repositories/stub_dto_repository.py
tests/__init__.py
tests/fixtures/__init__.py
tests/fixtures/data_models.py
tests/fixtures/dramatiq.py
tests/fixtures/dto_models.py
tests/fixtures/settings.py
tests/interfaces/__init__.py
tests/interfaces/data_model_repositories.py
tests/interfaces/data_models.py
tests/interfaces/dto_models.py
tests/interfaces/dto_repositories.py
tests/interfaces/settings.py
tests/test_helpers/__init__.py
tests/test_helpers/test_rabbitmq_helper.py
tests/test_interfaces/__init__.py
tests/test_interfaces/test_dto_model.py
tests/test_interfaces/test_dto_repository.py
tests/test_interfaces/test_rabbitmq_settings.py
tests/test_repositories/__init__.py
tests/test_repositories/test_data_model_repository.py
tests/test_repositories/test_settings_repository.py
tests/test_repositories/test_storage_repository.py
tests/test_repositories/test_stub_dto_repository.py
cbi_ddd-1.0.2.dist-info/LICENSE
cbi_ddd-1.0.2.dist-info/METADATA
cbi_ddd-1.0.2.dist-info/WHEEL
cbi_ddd-1.0.2.dist-info/top_level.txt
cbi_ddd-1.0.2.dist-info/zip-safe
cbi_ddd-1.0.2.dist-info/RECORD
